brainmri_ps/__init__.py
brainmri_ps/api.py
brainmri_ps/data.py
brainmri_ps/models.py
brainmri_ps/utils.py
brainmri_ps-1.1.1.dist-info/LICENSE.txt
brainmri_ps-1.1.1.dist-info/METADATA
brainmri_ps-1.1.1.dist-info/WHEEL
brainmri_ps-1.1.1.dist-info/top_level.txt
brainmri_ps-1.1.1.dist-info/RECORD
