Metadata-Version: 2.1
Name: brainmri-ps
Version: 1.1.1
Summary: Automatically classify Brain MRI series by pulse sequence types: FLAIR, T1C, T2, ADC, DWI, TOF and OTHER
Home-page: https://github.com/vantuan5644/MRI-Pulse-Sequence
Author: lhkhiem, tuantran
Author-email: 
License: LICENSE.txt
Project-URL: Bug Tracker, https://github.com/vantuan5644/MRI-Pulse-Sequence/issues
Platform: UNKNOWN
Classifier: Programming Language :: Python :: 3
Classifier: Operating System :: OS Independent
License-File: LICENSE.txt
Requires-Dist: wget (>=3.2)
Requires-Dist: gdown (>=3.11.0)
Requires-Dist: pydicom (>=2.1.1)
Requires-Dist: torch (>=1.8.1)
Requires-Dist: torchvision (>=0.9.1)
Requires-Dist: albumentations (>=0.1.12)
